LICENSE
sanctum/__init__.py
sanctum/client.py
sanctum/exceptions.py
sanctum/utils.py
sanctum_tc-0.8.0.dist-info/LICENSE
sanctum_tc-0.8.0.dist-info/METADATA
sanctum_tc-0.8.0.dist-info/WHEEL
sanctum_tc-0.8.0.dist-info/RECORD
