Metadata-Version: 2.1
Name: sanctum-tc
Version: 0.8.0
Summary: Library for interacting with the Sanctum API
License: MIT
Author: LightSage
Author-email: lightsage01@gmail.com
Requires-Python: >=3.8,<4.0
Classifier: License :: OSI Approved :: MIT License
Classifier: Programming Language :: Python :: 3
Classifier: Programming Language :: Python :: 3.8
Classifier: Programming Language :: Python :: 3.9
Classifier: Programming Language :: Python :: 3.10
Classifier: Programming Language :: Python :: 3.11
Classifier: Programming Language :: Python :: 3.12
Requires-Dist: aiohttp (>=3.6.0,<4.0.0)
